<?xml version="1.0" encoding="utf-8" ?>
<dwsync>
<file name="dropshadow.js" server="creativewildcat.com" local="129897845906216852" remote="129902550000000000" />
<file name="flickr-gallery.js" server="creativewildcat.com" local="129897845906796885" remote="129902550000000000" />
<file name="flickr.js" server="creativewildcat.com" local="129897845907096903" remote="129902550000000000" />
<file name="hoverIntent.js" server="creativewildcat.com" local="129897845907346917" remote="129902550000000000" />
<file name="ifixpng.js" server="creativewildcat.com" local="129897845907566929" remote="129902550000000000" />
<file name="jLoader.js" server="creativewildcat.com" local="129897845907816944" remote="129902550000000000" />
<file name="jquery-ui-1.8.21.custom.min.js" server="creativewildcat.com" local="129897845908036956" remote="129902550000000000" />
<file name="lightbox.js" server="creativewildcat.com" local="129897845908246968" remote="129902550000000000" />
<file name="timer.js" server="creativewildcat.com" local="129897845908396977" remote="129902550000000000" />
</dwsync>